setup.cfg
setup.py
pywimi/__init__.py
pywimi/wimi.py
pywimi.egg-info/PKG-INFO
pywimi.egg-info/SOURCES.txt
pywimi.egg-info/dependency_links.txt
pywimi.egg-info/top_level.txt