Metadata-Version: 1.0
Name: pywimi
Version: 0.3
Summary: Python wrapper for Wimi API
Home-page: https://github.com/davietk/pywimi.git
Author: Kevin Daviet
Author-email: davietk@gmail.com
License: MIT
Keywords: wimi,api
Platform: UNKNOWN
